pyipatcher/__init__.py
pyipatcher/__main__.py
pyipatcher/cli/ibootpatcher.py
pyipatcher/cli/kernelpatcher.py
pyipatcher/cli/ramdiskpatcher.py
pyipatcher/ipatcher.py
pyipatcher/logger.py
pyipatcher/patchfinder/asrpatchfinder.py
pyipatcher/patchfinder/ibootpatchfinder.py
pyipatcher/patchfinder/insn.py
pyipatcher/patchfinder/kernelpatchfinder.py
pyipatcher/patchfinder/patchfinder64.py
pyipatcher/patchfinder/rextpatchfinder.py
pyipatcher/wikiproxy.py
pyipatcher-2.0.5.dist-info/LICENSE
pyipatcher-2.0.5.dist-info/METADATA
pyipatcher-2.0.5.dist-info/WHEEL
pyipatcher-2.0.5.dist-info/entry_points.txt
pyipatcher-2.0.5.dist-info/RECORD
