Metadata-Version: 2.1
Name: pyipatcher
Version: 2.0.5
Summary: iOS ARM64 patchfinder & iOS ARM64 bootchain patcher
Home-page: https://github.com/Mini-Exploit/pyipatcher
License: GPL-3.0-only
Author: mini_exploit
Author-email: 61931266+Mini-Exploit@users.noreply.github.com
Requires-Python: >=3.7,<4.0
Classifier: License :: OSI Approved :: GNU General Public License v3 (GPLv3)
Classifier: Programming Language :: Python :: 3
Classifier: Programming Language :: Python :: 3.7
Classifier: Programming Language :: Python :: 3.8
Classifier: Programming Language :: Python :: 3.9
Classifier: Programming Language :: Python :: 3.10
Classifier: Programming Language :: Python :: 3.11
Requires-Dist: click (>=8.1.3,<9.0.0)
Requires-Dist: pyimg4 (>=0.7,<0.8)
Requires-Dist: pyquery (>=2.0.0,<3.0.0)
Project-URL: Bug Tracker, https://github.com/Mini-Exploit/pyipatcher/issues
Project-URL: Repository, https://github.com/Mini-Exploit/pyipatcher
